fmtex/__init__.py
fmtex/__main__.py
fmtex/generator.py
fmtex/lexer.py
fmtex-0.1.0.dist-info/licenses/LICENSE
fmtex-0.1.0.dist-info/METADATA
fmtex-0.1.0.dist-info/WHEEL
fmtex-0.1.0.dist-info/entry_points.txt
fmtex-0.1.0.dist-info/top_level.txt
fmtex-0.1.0.dist-info/RECORD
