Metadata-Version: 2.4
Name: fmtex
Version: 0.1.0
Summary: Write LaTeX math quickly.
License: MIT License
License-File: LICENSE
Requires-Dist: pyperclip
Requires-Dist: gnureadline; os_name != "nt"
Requires-Dist: pyreadline3; os_name == "nt"
Dynamic: license-file
